noctis/__init__.py
noctis/utilities.py
noctis/configuration/__init__.py
noctis/configuration/config.py
noctis/configuration/defaults.py
noctis/data_architecture/__init__.py
noctis/data_architecture/datacontainer.py
noctis/data_architecture/datamodel.py
noctis/data_architecture/graph_schema.py
noctis/data_transformation/__init__.py
noctis/data_transformation/data_styles/__init__.py
noctis/data_transformation/data_styles/dataframe_stylers.py
noctis/data_transformation/neo4j/neo4j_formatter.py
noctis/data_transformation/neo4j/stylers.py
noctis/data_transformation/postprocessing/__init__.py
noctis/data_transformation/postprocessing/chemdata_generators.py
noctis/data_transformation/preprocessing/__init__.py
noctis/data_transformation/preprocessing/core_graph_builder.py
noctis/data_transformation/preprocessing/data_preprocessing.py
noctis/data_transformation/preprocessing/graph_expander.py
noctis/data_transformation/preprocessing/utilities.py
noctis/repository/__init__.py
noctis/repository/neo4j/__init__.py
noctis/repository/neo4j/neo4j_functions.py
noctis/repository/neo4j/neo4j_queries.py
noctis/repository/neo4j/neo4j_repository.py
noctis-1.0.2.dist-info/licenses/LICENSE
noctis-1.0.2.dist-info/METADATA
noctis-1.0.2.dist-info/WHEEL
noctis-1.0.2.dist-info/entry_points.txt
noctis-1.0.2.dist-info/top_level.txt
noctis-1.0.2.dist-info/RECORD
