Metadata-Version: 2.4
Name: noctis
Version: 1.0.2
Classifier: Programming Language :: Python :: 3
Classifier: Programming Language :: Python :: 3 :: Only
Requires-Python: >=3.9
License-File: LICENSE
Requires-Dist: dynaconf
Requires-Dist: pyyaml
Requires-Dist: neo4j>=5.0.0
Requires-Dist: networkx
Requires-Dist: pandas>=2.0.0
Requires-Dist: pydantic>=2.0.0
Requires-Dist: tqdm
Requires-Dist: dask
Requires-Dist: dask[dataframe]
Requires-Dist: dask[distributed]
Requires-Dist: rdkit
Requires-Dist: linchemin>=3.0.0
Provides-Extra: dev
Requires-Dist: bumpver; extra == "dev"
Requires-Dist: pytest; extra == "dev"
Requires-Dist: pytest-cov; extra == "dev"
Requires-Dist: pytest-mock; extra == "dev"
Requires-Dist: sphinx; extra == "dev"
Requires-Dist: autodoc_pydantic; extra == "dev"
Requires-Dist: sphinxcontrib.mermaid; extra == "dev"
Requires-Dist: pre-commit; extra == "dev"
Requires-Dist: graphviz; extra == "dev"
Dynamic: license-file
